ebooklib/__init__.py
ebooklib/epub.py
ebooklib/utils.py
ebooklib/plugins/__init__.py
ebooklib/plugins/base.py
ebooklib/plugins/booktype.py
ebooklib/plugins/sourcecode.py
ebooklib/plugins/standard.py
ebooklib/plugins/tidyhtml.py
EbookLib_re-0.18.0.dist-info/AUTHORS.txt
EbookLib_re-0.18.0.dist-info/LICENSE.txt
EbookLib_re-0.18.0.dist-info/METADATA
EbookLib_re-0.18.0.dist-info/WHEEL
EbookLib_re-0.18.0.dist-info/top_level.txt
EbookLib_re-0.18.0.dist-info/RECORD
